color_ls-3.0.3.dist-info/licenses/LICENSE
colorls/__init__.py
colorls/__main__.py
colorls/colorls.py
colorls/config/colorls.toml
color_ls-3.0.3.dist-info/METADATA
color_ls-3.0.3.dist-info/WHEEL
color_ls-3.0.3.dist-info/entry_points.txt
color_ls-3.0.3.dist-info/top_level.txt
color_ls-3.0.3.dist-info/RECORD
