Metadata-Version: 2.4
Name: color-ls
Version: 3.0.3
Summary: Pure Python implementation of subset of ls command with colors and icons
Author-email: Romeet <compilation-error@proton.me>
License-Expression: GPL-3.0-or-later
Project-URL: Homepage, https://codeberg.org/compilation-error/colorls
Project-URL: Repository, https://codeberg.org/compilation-error/colorls.git
Project-URL: Issues, https://codeberg.org/compilation-error/colorls/issues
Classifier: Development Status :: 4 - Beta
Classifier: Programming Language :: Python :: 3
Classifier: Operating System :: OS Independent
Classifier: Topic :: Utilities
Requires-Python: >=3.10
License-File: LICENSE
Dynamic: license-file
